{"nodes": [{"id": "docs_roadmap_fase2", "label": "Fronda CMMS Roadmap Fase 2 y Prompt de Ejecuci\u00f3n", "file_type": "document", "source_file": "docs/ROADMAP-FASE-2.md", "source_location": null, "source_url": null, "captured_at": null, "author": null, "contributor": null}, {"id": "bug_duplicate_listeners", "label": "Bug: Listeners Registrados Dos Veces (doble notificaci\u00f3n/webhook en producci\u00f3n)", "file_type": "rationale", "source_file": "docs/ROADMAP-FASE-2.md", "source_location": null, "source_url": null, "captured_at": null, "author": null, "contributor": null}, {"id": "gap_overlapping_downtime", "label": "F1: Paros Solapados Cuentan Horas Dos Veces", "file_type": "rationale", "source_file": "docs/ROADMAP-FASE-2.md", "source_location": null, "source_url": null, "captured_at": null, "author": null, "contributor": null}, {"id": "gap_downtime_crossing_months", "label": "F2: Paros a Caballo Entre Meses Distorsionan Cierre Mensual", "file_type": "rationale", "source_file": "docs/ROADMAP-FASE-2.md", "source_location": null, "source_url": null, "captured_at": null, "author": null, "contributor": null}], "edges": [{"source": "docs_roadmap_fase2", "target": "docs_auditoria", "relation": "cites", "confidence": "EXTRACTED", "confidence_score": 1.0, "source_file": "docs/ROADMAP-FASE-2.md", "source_location": null, "weight": 1.0}, {"source": "docs_roadmap_fase2", "target": "docs_prompt_roadmap", "relation": "semantically_similar_to", "confidence": "INFERRED", "confidence_score": 0.85, "source_file": "docs/ROADMAP-FASE-2.md", "source_location": null, "weight": 1.0}, {"source": "docs_roadmap_fase2", "target": "feature_work_order_tasks_checklist", "relation": "references", "confidence": "EXTRACTED", "confidence_score": 1.0, "source_file": "docs/ROADMAP-FASE-2.md", "source_location": null, "weight": 1.0}, {"source": "docs_roadmap_fase2", "target": "feature_preventive_wo_generator", "relation": "references", "confidence": "EXTRACTED", "confidence_score": 1.0, "source_file": "docs/ROADMAP-FASE-2.md", "source_location": null, "weight": 1.0}, {"source": "docs_roadmap_fase2", "target": "feature_downtime_events_v2", "relation": "references", "confidence": "EXTRACTED", "confidence_score": 1.0, "source_file": "docs/ROADMAP-FASE-2.md", "source_location": null, "weight": 1.0}, {"source": "docs_roadmap_fase2", "target": "feature_meter_projection", "relation": "references", "confidence": "EXTRACTED", "confidence_score": 1.0, "source_file": "docs/ROADMAP-FASE-2.md", "source_location": null, "weight": 1.0}, {"source": "docs_roadmap_fase2", "target": "feature_plant_kpis", "relation": "references", "confidence": "EXTRACTED", "confidence_score": 1.0, "source_file": "docs/ROADMAP-FASE-2.md", "source_location": null, "weight": 1.0}, {"source": "docs_roadmap_fase2", "target": "feature_historical_data_migration", "relation": "references", "confidence": "EXTRACTED", "confidence_score": 1.0, "source_file": "docs/ROADMAP-FASE-2.md", "source_location": null, "weight": 1.0}, {"source": "docs_roadmap_fase2", "target": "bug_duplicate_listeners", "relation": "references", "confidence": "EXTRACTED", "confidence_score": 1.0, "source_file": "docs/ROADMAP-FASE-2.md", "source_location": null, "weight": 1.0}, {"source": "docs_roadmap_fase2", "target": "gap_overlapping_downtime", "relation": "references", "confidence": "EXTRACTED", "confidence_score": 1.0, "source_file": "docs/ROADMAP-FASE-2.md", "source_location": null, "weight": 1.0}, {"source": "docs_roadmap_fase2", "target": "gap_downtime_crossing_months", "relation": "references", "confidence": "EXTRACTED", "confidence_score": 1.0, "source_file": "docs/ROADMAP-FASE-2.md", "source_location": null, "weight": 1.0}, {"source": "gap_overlapping_downtime", "target": "table_equipment_downtime_events", "relation": "rationale_for", "confidence": "EXTRACTED", "confidence_score": 1.0, "source_file": "docs/ROADMAP-FASE-2.md", "source_location": null, "weight": 1.0}, {"source": "bug_duplicate_listeners", "target": "feature_preventive_wo_generator", "relation": "conceptually_related_to", "confidence": "INFERRED", "confidence_score": 0.75, "source_file": "docs/ROADMAP-FASE-2.md", "source_location": null, "weight": 1.0}], "hyperedges": [{"id": "roadmap_execution_flow", "label": "Fronda Audit-to-Roadmap Execution Flow", "nodes": ["docs_auditoria", "docs_prompt_roadmap", "docs_roadmap_fase2"], "relation": "participate_in", "confidence": "EXTRACTED", "confidence_score": 0.9, "source_file": "docs/ROADMAP-FASE-2.md"}]}